odoo10_addon_stock_picking_filter_lot-10.0.1.0.0-py2.7-nspkg.pth
odoo/addons/stock_picking_filter_lot/README.rst
odoo/addons/stock_picking_filter_lot/__init__.py
odoo/addons/stock_picking_filter_lot/__manifest__.py
odoo/addons/stock_picking_filter_lot/i18n/it.po
odoo/addons/stock_picking_filter_lot/models/__init__.py
odoo/addons/stock_picking_filter_lot/models/stock_pack_operation.py
odoo/addons/stock_picking_filter_lot/models/stock_production_lot.py
odoo/addons/stock_picking_filter_lot/views/stock_pack_operation.xml
odoo10_addon_stock_picking_filter_lot-10.0.1.0.0.dist-info/DESCRIPTION.rst
odoo10_addon_stock_picking_filter_lot-10.0.1.0.0.dist-info/METADATA
odoo10_addon_stock_picking_filter_lot-10.0.1.0.0.dist-info/RECORD
odoo10_addon_stock_picking_filter_lot-10.0.1.0.0.dist-info/WHEEL
odoo10_addon_stock_picking_filter_lot-10.0.1.0.0.dist-info/metadata.json
odoo10_addon_stock_picking_filter_lot-10.0.1.0.0.dist-info/namespace_packages.txt
odoo10_addon_stock_picking_filter_lot-10.0.1.0.0.dist-info/top_level.txt
