Metadata-Version: 2.0
Name: odoo10-addon-stock-picking-filter-lot
Version: 10.0.1.0.0
Summary: In picking out lots' selection, filter lots based on their location
Home-page: https://github.com/OCA/stock-logistics-workflow/tree/10.0/stock_filter_lots
Author: Agile Business Group, Odoo Community Association (OCA)
Author-email: support@odoo-community.org
License: AGPL-3
Platform: UNKNOWN
Classifier: Programming Language :: Python
Classifier: Framework :: Odoo
Classifier: License :: OSI Approved :: GNU Affero General Public License v3
Requires-Python: ~=2.7
Requires-Dist: odoo (<10.1dev,>=10.0)
